Workbook

Sheet Cover
A1: FX Transaction Hedge Model — Aerospace EUR Receivable
A3: Firm | B3: U.S. Aerospace Manufacturer
A4: Scenario | B4: aerospace
A5: Exposure | B5: EUR 20,000,000 receivable, 365-day settlement
A6: Author | B6: Kailani Phillips
A7: Role | B7: Treasury Analyst / FP&A Analyst
A8: Audience | B8: CFO / Director of Treasury
A9: Date built | B9: 2026-07-31
A10: Source spec | B10: docs/specs/2026-07-31-Phillips-aerospace-spec.md
A12: Data Provenance (placeholders — indicative, replaced with live data at Stage 4)
A13: Named range | B13: Value | C13: Source | D13: Access date
A14: S0_in | B14: 1.1505 | C14: Yahoo Finance / Investing.com, EURUSD spot | D14: 2026-07-31
A15: F0_in | B15: 1.0935 | C15: Scenario-assigned indicative forward (course scenarios.md) | D15: 2026-07-24
A16: R_USD | B16: 3.63% | C16: Federal Reserve H.15, effective federal funds rate | D16: 2026-07-31
A17: R_FC | B17: 2.25% | C17: ECB deposit facility rate | D17: 2026-07-31
A18: PREM_PUT / PREM_CALL | B18: $0.019 / $0.024 | C18: Scenario-assigned indicative option premiums | D18: 2026-07-24
A20: Note: F0_in was set independently of today's S0_in / R_USD / R_FC, so the parity check on the MoneyMarket tab shows a real, material gap in this draft — flagged, not hidden. See Notes & Assumptions tab and the build audit note.

Sheet Legend-Key
A1: Legend / Key
A3: Sample | B3: Inputs — Market data or contract terms an analyst may adjust (spot, rates, strikes, premia).
A4: Sample | B4: Assumptions — Modeling conventions chosen by the analyst (day-count basis, grid step size).
A5: Sample | B5: Formulas — Intermediate calculation cells — always formulas, never typed numbers.
A6: Sample | B6: Outputs — Named summary results shown to the CFO (still formulas, highlighted as headline results).

Sheet Inputs
A1: Inputs — Named-Range Contract
A3: Named range | B3: Value | C3: Unit | D3: Category | E3: Source / Notes
A4: FC_AMT | B4: 20000000 | C4: EUR | D4: Input | E4: Fixed by sales contract; unchanged at Stage 4
A5: S0_in | B5: 1.1505 | C5: USD/EUR | D5: Input | E5: Yahoo Finance/Bloomberg EURUSD spot at Stage-4 market close (indicative)
A6: F0_in | B6: 1.0935 | C6: USD/EUR | D6: Input | E6: Scenario-assigned; replaced with live 1Y outright forward at Stage 4 (indicative)
A7: R_USD | B7: 0.0363 | C7: Annual % | D7: Input | E7: Fed H.15 effective federal funds rate at Stage 4 (indicative)
A8: R_FC | B8: 0.0225 | C8: Annual % | D8: Input | E8: ECB deposit facility rate / EURIBOR equivalent at Stage 4 (indicative)
A9: T_DAYS | B9: 365 | C9: Days | D9: Input | E9: Fixed by contract
A10: K_PUT | B10: 1.1505 | C10: USD/EUR | D10: Input | E10: Exactly at S0_in, no rounding (indicative; reset at Stage 4)
A11: K_CALL | B11: 1.1505 | C11: USD/EUR | D11: Input | E11: Retained for template symmetry — not used in this receivable-only build
A12: PREM_PUT | B12: 0.019 | C12: USD | D12: Input | E12: Scenario-assigned; replaced with live options-desk quote at Stage 4 (indicative)
A13: PREM_CALL | B13: 0.024 | C13: USD | D13: Input | E13: Retained for template symmetry — not used in this receivable-only build
A15: Modeling Conventions (assumptions)
A16: BASIS_USD | B16: 360 | C16: Days | D16: Assumption | E16: ACT/360, standard USD money-market convention
A17: BASIS_FC | B17: 365 | C17: Days | D17: Assumption | E17: ACT/365 per course convention (real EURIBOR is typically ACT/360 — flagged)
A18: STEP_FRAC | B18: 0.01 | C18: % | D18: Assumption | E18: Sensitivity grid step size
A20: Derived Values
A21: DF_USD | B21: =1+R_USD*T_DAYS/BASIS_USD -> 1.0368042 | C21: factor | D21: Formula | E21: USD accumulation factor to settlement
A22: DF_FC | B22: =1+R_FC*T_DAYS/BASIS_FC -> 1.0225 | C22: factor | D22: Formula | E22: EUR accumulation factor to settlement
A23: FV_PREM_PUT | B23: =-PREM_PUT*FC_AMT*DF_USD -> -393985.58 | C23: USD | D23: Formula | E23: Future value of put premium at settlement
A24: FV_PREM_CALL | B24: =-PREM_CALL*FC_AMT*DF_USD -> -497666 | C24: USD | D24: Formula | E24: Future value of call premium (reference only, unused)

Sheet Forward
A1: Forward Hedge — Certainty Benchmark
A3: USD Proceeds (Forward) | B3: =FC_AMT*F0_in -> 21870000
A5: Locked at inception (FC_AMT × F0_in); invariant across the S_T sensitivity grid. This is the certainty benchmark the money-market and option hedges are measured against.

Sheet MoneyMarket
A1: Money-Market Hedge — Parity Check
A3: Step 1: Borrow FC_AMT / DF_FC euros today | B3: =FC_AMT/DF_FC -> 19559902
A4: Step 2: Convert to USD at spot | B4: =B3*S0_in -> 22503667
A5: Step 3: Invest USD to maturity (USD_MM) | B5: =B4*DF_USD -> 23331896
A7: Covered Interest Parity Check
A8: F_Implied = S0_in × DF_USD / DF_FC | B8: =S0_in*DF_USD/DF_FC -> 1.1665948
A9: F0_in (quoted forward) | B9: =F0_in -> 1.0935
A10: Absolute rate difference | B10: =ABS(B8-B9) -> 0.073094811
A11: Relative difference — USD_MM vs USD_FWD | B11: =ABS(B5-Forward!B3)/Forward!B3 -> 0.06684482
A12: Parity check result (tolerance 0.05%) | B12: =IF(B11<=0.0005,"PASS","FAIL") -> FAIL
A14: Expected result in this draft: FAIL. F0_in is a scenario-assigned placeholder set independently of the S0_in/R_USD/R_FC pulled today, so this gap is a known, documented data-consistency issue (see spec §4 and Notes & Assumptions), not a formula defect. It must be re-verified once Stage 4 supplies mutually consistent, same-timestamp live data.

Sheet Options
A1: Option Hedge — Put Floor (receivable)
A3: USD Proceeds — Put, at baseline S_T = S0_in | B3: =MAX(S0_in,K_PUT)*FC_AMT+FV_PREM_PUT -> 22616014
A4: USD Proceeds — Call, at baseline S_T = S0_in (reference only) | B4: =MIN(S0_in,K_CALL)*FC_AMT+FV_PREM_CALL -> 22512334
A6: The put is the primary hedge for this receivable: below K_PUT it pays the difference (floor holds); above it, the put expires worthless and proceeds track spot, net of the premium paid either way. The call is computed only for template symmetry with the payable mirror and is not part of the recommended hedge for this receivable scenario.
A8: Put Continuity Check (kink verification)
A9: Put payoff formula evaluated at S_T = K_PUT | B9: =MAX(K_PUT,K_PUT)*FC_AMT+FV_PREM_PUT -> 22616014
A10: Expected value: K_PUT × FC_AMT + FV_PREM_PUT | B10: =K_PUT*FC_AMT+FV_PREM_PUT -> 22616014
A11: Match? | B11: =IF(ABS(B9-B10)<1,"PASS","FAIL") -> PASS

Sheet Sensitivity
A1: Sensitivity — S_T from 0.95×S0_in to 1.05×S0_in, 1% steps | N1: Winner labels | O1: Active-hedge labels
N2: No Hedge | O2: Forward
A3: n | B3: S_T | C3: No Hedge | D3: Forward | E3: Money Market | F3: Option (Put) | G3: Option (Call, ref.) | H3: HP Forward | I3: HP MM | J3: HP Put | K3: Overall Winner | L3: Best Active Hedge | N3: Forward | O3: Money Market
A4: -5 | B4: =S0_in*(1+A4*STEP_FRAC) -> 1.092975 | C4: =B4*FC_AMT -> 21859500 | D4: =Forward!$B$3 -> 21870000 | E4: =MoneyMarket!$B$5 -> 23331896 | F4: =MAX(B4,K_PUT)*FC_AMT+FV_PREM_PUT -> 22616014 | G4: =MIN(B4,K_CALL)*FC_AMT+FV_PREM_CALL -> 21361834 | H4: =D4-C4 -> 10500 | I4: =E4-C4 -> 1472396.2 | J4: =F4-C4 -> 756514.42 | K4: =INDEX($N$2:$N$5,MATCH(MAX(C4:F4),C4:F4,0)) -> Money Market | L4: =INDEX($O$2:$O$4,MATCH(MAX(D4:F4),D4:F4,0)) -> Money Market | N4: Money Market | O4: Option (Put)
A5: -4 | B5: =S0_in*(1+A5*STEP_FRAC) -> 1.10448 | C5: =B5*FC_AMT -> 22089600 | D5: =Forward!$B$3 -> 21870000 | E5: =MoneyMarket!$B$5 -> 23331896 | F5: =MAX(B5,K_PUT)*FC_AMT+FV_PREM_PUT -> 22616014 | G5: =MIN(B5,K_CALL)*FC_AMT+FV_PREM_CALL -> 21591934 | H5: =D5-C5 -> -219600 | I5: =E5-C5 -> 1242296.2 | J5: =F5-C5 -> 526414.42 | K5: =INDEX($N$2:$N$5,MATCH(MAX(C5:F5),C5:F5,0)) -> Money Market | L5: =INDEX($O$2:$O$4,MATCH(MAX(D5:F5),D5:F5,0)) -> Money Market | N5: Option (Put)
A6: -3 | B6: =S0_in*(1+A6*STEP_FRAC) -> 1.115985 | C6: =B6*FC_AMT -> 22319700 | D6: =Forward!$B$3 -> 21870000 | E6: =MoneyMarket!$B$5 -> 23331896 | F6: =MAX(B6,K_PUT)*FC_AMT+FV_PREM_PUT -> 22616014 | G6: =MIN(B6,K_CALL)*FC_AMT+FV_PREM_CALL -> 21822034 | H6: =D6-C6 -> -449700 | I6: =E6-C6 -> 1012196.2 | J6: =F6-C6 -> 296314.42 | K6: =INDEX($N$2:$N$5,MATCH(MAX(C6:F6),C6:F6,0)) -> Money Market | L6: =INDEX($O$2:$O$4,MATCH(MAX(D6:F6),D6:F6,0)) -> Money Market
A7: -2 | B7: =S0_in*(1+A7*STEP_FRAC) -> 1.12749 | C7: =B7*FC_AMT -> 22549800 | D7: =Forward!$B$3 -> 21870000 | E7: =MoneyMarket!$B$5 -> 23331896 | F7: =MAX(B7,K_PUT)*FC_AMT+FV_PREM_PUT -> 22616014 | G7: =MIN(B7,K_CALL)*FC_AMT+FV_PREM_CALL -> 22052134 | H7: =D7-C7 -> -679800 | I7: =E7-C7 -> 782096.21 | J7: =F7-C7 -> 66214.417 | K7: =INDEX($N$2:$N$5,MATCH(MAX(C7:F7),C7:F7,0)) -> Money Market | L7: =INDEX($O$2:$O$4,MATCH(MAX(D7:F7),D7:F7,0)) -> Money Market
A8: -1 | B8: =S0_in*(1+A8*STEP_FRAC) -> 1.138995 | C8: =B8*FC_AMT -> 22779900 | D8: =Forward!$B$3 -> 21870000 | E8: =MoneyMarket!$B$5 -> 23331896 | F8: =MAX(B8,K_PUT)*FC_AMT+FV_PREM_PUT -> 22616014 | G8: =MIN(B8,K_CALL)*FC_AMT+FV_PREM_CALL -> 22282234 | H8: =D8-C8 -> -909900 | I8: =E8-C8 -> 551996.21 | J8: =F8-C8 -> -163885.58 | K8: =INDEX($N$2:$N$5,MATCH(MAX(C8:F8),C8:F8,0)) -> Money Market | L8: =INDEX($O$2:$O$4,MATCH(MAX(D8:F8),D8:F8,0)) -> Money Market
A9: 0 | B9: =S0_in*(1+A9*STEP_FRAC) -> 1.1505 | C9: =B9*FC_AMT -> 23010000 | D9: =Forward!$B$3 -> 21870000 | E9: =MoneyMarket!$B$5 -> 23331896 | F9: =MAX(B9,K_PUT)*FC_AMT+FV_PREM_PUT -> 22616014 | G9: =MIN(B9,K_CALL)*FC_AMT+FV_PREM_CALL -> 22512334 | H9: =D9-C9 -> -1140000 | I9: =E9-C9 -> 321896.21 | J9: =F9-C9 -> -393985.58 | K9: =INDEX($N$2:$N$5,MATCH(MAX(C9:F9),C9:F9,0)) -> Money Market | L9: =INDEX($O$2:$O$4,MATCH(MAX(D9:F9),D9:F9,0)) -> Money Market
A10: 1 | B10: =S0_in*(1+A10*STEP_FRAC) -> 1.162005 | C10: =B10*FC_AMT -> 23240100 | D10: =Forward!$B$3 -> 21870000 | E10: =MoneyMarket!$B$5 -> 23331896 | F10: =MAX(B10,K_PUT)*FC_AMT+FV_PREM_PUT -> 22846114 | G10: =MIN(B10,K_CALL)*FC_AMT+FV_PREM_CALL -> 22512334 | H10: =D10-C10 -> -1370100 | I10: =E10-C10 -> 91796.21 | J10: =F10-C10 -> -393985.58 | K10: =INDEX($N$2:$N$5,MATCH(MAX(C10:F10),C10:F10,0)) -> Money Market | L10: =INDEX($O$2:$O$4,MATCH(MAX(D10:F10),D10:F10,0)) -> Money Market
A11: 2 | B11: =S0_in*(1+A11*STEP_FRAC) -> 1.17351 | C11: =B11*FC_AMT -> 23470200 | D11: =Forward!$B$3 -> 21870000 | E11: =MoneyMarket!$B$5 -> 23331896 | F11: =MAX(B11,K_PUT)*FC_AMT+FV_PREM_PUT -> 23076214 | G11: =MIN(B11,K_CALL)*FC_AMT+FV_PREM_CALL -> 22512334 | H11: =D11-C11 -> -1600200 | I11: =E11-C11 -> -138303.79 | J11: =F11-C11 -> -393985.58 | K11: =INDEX($N$2:$N$5,MATCH(MAX(C11:F11),C11:F11,0)) -> No Hedge | L11: =INDEX($O$2:$O$4,MATCH(MAX(D11:F11),D11:F11,0)) -> Money Market
A12: 3 | B12: =S0_in*(1+A12*STEP_FRAC) -> 1.185015 | C12: =B12*FC_AMT -> 23700300 | D12: =Forward!$B$3 -> 21870000 | E12: =MoneyMarket!$B$5 -> 23331896 | F12: =MAX(B12,K_PUT)*FC_AMT+FV_PREM_PUT -> 23306314 | G12: =MIN(B12,K_CALL)*FC_AMT+FV_PREM_CALL -> 22512334 | H12: =D12-C12 -> -1830300 | I12: =E12-C12 -> -368403.79 | J12: =F12-C12 -> -393985.58 | K12: =INDEX($N$2:$N$5,MATCH(MAX(C12:F12),C12:F12,0)) -> No Hedge | L12: =INDEX($O$2:$O$4,MATCH(MAX(D12:F12),D12:F12,0)) -> Money Market
A13: 4 | B13: =S0_in*(1+A13*STEP_FRAC) -> 1.19652 | C13: =B13*FC_AMT -> 23930400 | D13: =Forward!$B$3 -> 21870000 | E13: =MoneyMarket!$B$5 -> 23331896 | F13: =MAX(B13,K_PUT)*FC_AMT+FV_PREM_PUT -> 23536414 | G13: =MIN(B13,K_CALL)*FC_AMT+FV_PREM_CALL -> 22512334 | H13: =D13-C13 -> -2060400 | I13: =E13-C13 -> -598503.79 | J13: =F13-C13 -> -393985.58 | K13: =INDEX($N$2:$N$5,MATCH(MAX(C13:F13),C13:F13,0)) -> No Hedge | L13: =INDEX($O$2:$O$4,MATCH(MAX(D13:F13),D13:F13,0)) -> Option (Put)
A14: 5 | B14: =S0_in*(1+A14*STEP_FRAC) -> 1.208025 | C14: =B14*FC_AMT -> 24160500 | D14: =Forward!$B$3 -> 21870000 | E14: =MoneyMarket!$B$5 -> 23331896 | F14: =MAX(B14,K_PUT)*FC_AMT+FV_PREM_PUT -> 23766514 | G14: =MIN(B14,K_CALL)*FC_AMT+FV_PREM_CALL -> 22512334 | H14: =D14-C14 -> -2290500 | I14: =E14-C14 -> -828603.79 | J14: =F14-C14 -> -393985.58 | K14: =INDEX($N$2:$N$5,MATCH(MAX(C14:F14),C14:F14,0)) -> No Hedge | L14: =INDEX($O$2:$O$4,MATCH(MAX(D14:F14),D14:F14,0)) -> Option (Put)
A16: Baseline row (n=0, S_T = S0_in) is row 9. Grid index n (-5..5) is a structural row label, not a market input; every $ value in columns B-L is a live formula that recalculates when Inputs-tab values change.

Sheet Notes-Assumptions
A1: Notes & Assumptions
A3: • Quote convention: all rates expressed as USD per EUR. A higher quote means EUR appreciation.
A5: • Horizon: single-maturity model; T_DAYS = 365.
A7: • Day-count basis: BASIS_USD = 360 (ACT/360, standard USD money-market convention); BASIS_FC = 365 (ACT/365, per this course's stated convention for EUR legs — real-world EURIBOR is typically ACT/360; this divergence is intentional per the course template, not an error).
A9: • Parity: the money-market hedge is assumed to replicate the forward hedge under covered interest-rate parity. In this draft, F0_in was set independently of S0_in/R_USD/R_FC, so the MoneyMarket tab's parity check shows a real, material gap — expected, documented, and to be re-verified at Stage 4 with mutually consistent live data.
A11: • Option premium: paid upfront in USD, quoted per 1 unit of EUR (no contract multiplier). Premia are a negative cash flow at t0, carried forward at R_USD via DF_USD.
A13: • Counterparty/credit risk: excluded. All derivatives assumed frictionless and creditworthy.
A15: • Transaction costs & bid-ask spreads: excluded from this base case; flagged as a Stage 4 candidate.
A17: • Tax/accounting treatment: excluded. Model reports pre-tax cash outcomes only.
A19: • Scenario construction: S_T is varied deterministically across an 11-point grid; no probability weights or implied-volatility distribution are applied.
A21: • K_CALL and PREM_CALL are retained for template symmetry with the payable-side mirror hedge; they are not part of the recommended hedge for this EUR receivable.
